devcontainer_contrib/__init__.py
devcontainer_contrib/__main__.py
devcontainer_contrib/cli/__init__.py
devcontainer_contrib/cli/features.py
devcontainer_contrib/features_generation/__init__.py
devcontainer_contrib/features_generation/dir_modules/__init__.py
devcontainer_contrib/features_generation/dir_modules/src_dir.py
devcontainer_contrib/features_generation/dir_modules/test_dir.py
devcontainer_contrib/features_generation/file_models/__init__.py
devcontainer_contrib/features_generation/file_models/dependencies_sh.py
devcontainer_contrib/features_generation/file_models/devcontainer_feature_json.py
devcontainer_contrib/features_generation/file_models/install_command_sh.py
devcontainer_contrib/features_generation/file_models/install_sh.py
devcontainer_contrib/features_generation/file_models/scenarios_json.py
devcontainer_contrib/features_generation/file_models/test_sh.py
devcontainer_contrib/models/__init__.py
devcontainer_contrib/models/devcontainer_feature.py
devcontainer_contrib/models/devcontainer_feature_definition.py
devcontainer_contrib-0.0.26.dist-info/METADATA
devcontainer_contrib-0.0.26.dist-info/WHEEL
devcontainer_contrib-0.0.26.dist-info/entry_points.txt
devcontainer_contrib-0.0.26.dist-info/top_level.txt
devcontainer_contrib-0.0.26.dist-info/RECORD
