Metadata-Version: 2.1
Name: devcontainer-contrib
Version: 0.0.26
Requires-Dist: pydantic (==1.10.5)
Requires-Dist: typer
Provides-Extra: dev
Requires-Dist: pytest ; extra == 'dev'
Requires-Dist: pytest-shell-utilities ; extra == 'dev'
Requires-Dist: black ; extra == 'dev'
Requires-Dist: mypy ; extra == 'dev'
Provides-Extra: generate
Requires-Dist: easyfs (==0.0.3) ; extra == 'generate'
